onelogin/__init__.py
onelogin/api_client.py
onelogin/api_response.py
onelogin/configuration.py
onelogin/exceptions.py
onelogin/rest.py
onelogin/api/__init__.py
onelogin/api/api_auth_claims_api.py
onelogin/api/api_auth_client_apps_api.py
onelogin/api/api_auth_scopes_api.py
onelogin/api/api_authorization_server_api.py
onelogin/api/app_rules_api.py
onelogin/api/apps_api.py
onelogin/api/branding_service_api.py
onelogin/api/branding_service_smtp_api.py
onelogin/api/branding_service_templates_api.py
onelogin/api/events_api.py
onelogin/api/groups_api.py
onelogin/api/invite_links_api.py
onelogin/api/multi_factor_authentication_api.py
onelogin/api/multi_factor_authentication_v1_api.py
onelogin/api/o_auth2_api.py
onelogin/api/privileges_api.py
onelogin/api/roles_api.py
onelogin/api/saml_assertions_api.py
onelogin/api/smart_hooks_api.py
onelogin/api/user_mappings_api.py
onelogin/api/users_v1_api.py
onelogin/api/users_v2_api.py
onelogin/api/vigilance_ai_api.py
onelogin/models/__init__.py
onelogin/models/action_obj.py
onelogin/models/activate_mfa_factors_request.py
onelogin/models/add_client_app201_response.py
onelogin/models/add_client_app_request.py
onelogin/models/add_privilege_to_role201_response.py
onelogin/models/add_privilege_to_role_request.py
onelogin/models/add_roles_to_user_request.py
onelogin/models/alt_err.py
onelogin/models/app_parameters.py
onelogin/models/app_rule.py
onelogin/models/assign_users_to_privilege_request.py
onelogin/models/auth_claim.py
onelogin/models/auth_id.py
onelogin/models/auth_method.py
onelogin/models/auth_scope.py
onelogin/models/auth_server.py
onelogin/models/auth_server_configuration.py
onelogin/models/brand.py
onelogin/models/brand_app.py
onelogin/models/brand_background.py
onelogin/models/brand_background_urls.py
onelogin/models/brand_logo.py
onelogin/models/brand_logo_urls.py
onelogin/models/brand_req.py
onelogin/models/client_app_full.py
onelogin/models/clock_counter.py
onelogin/models/condition.py
onelogin/models/configuration_oidc.py
onelogin-3.2.3.dist-info/METADATA
onelogin-3.2.3.dist-info/WHEEL
onelogin-3.2.3.dist-info/top_level.txt
onelogin-3.2.3.dist-info/RECORD
