Metadata-Version: 2.4
Name: onelogin
Version: 3.2.3
Summary: OneLogin API Python SDK
Author-email: OneLogin <developers@onelogin.com>
License: NoLicense
Project-URL: Repository, https://github.com/onelogin/onelogin-python-sdk
Keywords: OneLogin,SDK,API
Requires-Python: >=3.7
Requires-Dist: urllib3>=2.0.2
Requires-Dist: python-dateutil>=2.5.3
Requires-Dist: pydantic>=2.11.0
Requires-Dist: aenum>=3.1.11
Requires-Dist: setuptools>=67.7.1
Provides-Extra: test
Requires-Dist: pytest~=7.1.3; extra == "test"
Requires-Dist: pytest-cov>=2.8.1; extra == "test"
Requires-Dist: pytest-randomly>=3.12.0; extra == "test"
Requires-Dist: flake8>=4.0.0; extra == "test"
Requires-Dist: tox>=3.9.0; extra == "test"
